random_geometry_points/__init__.py
random_geometry_points/circle2d.py
random_geometry_points/geometry.py
random_geometry_points/plane.py
random_geometry_points/sphere.py
random_geometry_points/validation.py
random_geometry_points/vector_math.py
random_geometry_points-1.1.2.dist-info/METADATA
random_geometry_points-1.1.2.dist-info/RECORD
random_geometry_points-1.1.2.dist-info/WHEEL
random_geometry_points-1.1.2.dist-info/top_level.txt
