Metadata-Version: 2.1
Name: random_geometry_points
Version: 1.1.2
Summary: Library to generate random points (2D or 3D) on geometry surfaces
Home-page: https://github.com/brauls/random-geometry-points
Author: Benedikt Rauls
Author-email: brauls101@gmail.com
License: MIT
Project-URL: Source, https://github.com/brauls/random-geometry-points
Project-URL: Tracker, https://github.com/brauls/random-geometry-points/issues
Keywords: geometry random points 2D 3D
Platform: UNKNOWN
Classifier: Development Status :: 4 - Beta
Classifier: Intended Audience :: Developers
Classifier: License :: OSI Approved :: MIT License
Classifier: Programming Language :: Python :: 3.6
Requires-Python: >=3.6
